bayestorch/__init__.py
bayestorch/py.typed
bayestorch/version.py
bayestorch/distributions/__init__.py
bayestorch/distributions/cat_distribution.py
bayestorch/distributions/constraints.py
bayestorch/distributions/deterministic.py
bayestorch/distributions/finite.py
bayestorch/distributions/log_scale_normal.py
bayestorch/distributions/softplus_inv_scale_normal.py
bayestorch/distributions/utils.py
bayestorch/nn/__init__.py
bayestorch/nn/particle_posterior_module.py
bayestorch/nn/prior_module.py
bayestorch/nn/utils.py
bayestorch/nn/variational_posterior_module.py
bayestorch/optim/__init__.py
bayestorch/optim/sghmc.py
bayestorch/optim/sgld.py
bayestorch/optim/svgd.py
bayestorch-0.0.3.dist-info/LICENSE
bayestorch-0.0.3.dist-info/METADATA
bayestorch-0.0.3.dist-info/NOTICE
bayestorch-0.0.3.dist-info/WHEEL
bayestorch-0.0.3.dist-info/top_level.txt
bayestorch-0.0.3.dist-info/RECORD
