Metadata-Version: 2.1
Name: bayestorch
Version: 0.0.3
Summary: Lightweight Bayesian deep learning library for fast prototyping based on PyTorch
Home-page: https://github.com/lucadellalib/bayestorch
Author: Luca Della Libera
Author-email: luca.dellalib@gmail.com
License: Apache License 2.0
Keywords: Bayesian deep learning,PyTorch
Platform: OS Independent
Classifier: Development Status :: 3 - Alpha
Classifier: Environment :: Console
Classifier: Environment :: GPU :: NVIDIA CUDA
Classifier: Intended Audience :: Developers
Classifier: Intended Audience :: Information Technology
Classifier: Intended Audience :: Science/Research
Classifier: License :: OSI Approved :: Apache Software License
Classifier: Natural Language :: English
Classifier: Operating System :: OS Independent
Classifier: Programming Language :: Python :: 3
Classifier: Programming Language :: Python :: 3.6
Classifier: Programming Language :: Python :: 3.7
Classifier: Programming Language :: Python :: 3.8
Classifier: Programming Language :: Python :: 3.9
Classifier: Programming Language :: Python :: 3.10
Classifier: Programming Language :: Python :: 3 :: Only
Classifier: Topic :: Scientific/Engineering :: Artificial Intelligence
Classifier: Topic :: Software Development :: Libraries :: Python Modules
Classifier: Typing :: Typed
Requires-Python: >=3.6
License-File: LICENSE
License-File: NOTICE
Requires-Dist: torch (>=1.5.0)
Provides-Extra: dev
Requires-Dist: black (>=22.3.0) ; extra == 'dev'
Requires-Dist: cibuildwheel (>=2.3.1) ; extra == 'dev'
Requires-Dist: flake8 (>=3.8.3) ; extra == 'dev'
Requires-Dist: flake8-bugbear (>=20.1.4) ; extra == 'dev'
Requires-Dist: isort (>=5.4.2) ; extra == 'dev'
Requires-Dist: pre-commit (>=2.6.0) ; extra == 'dev'
Requires-Dist: pre-commit-hooks (>=3.2.0) ; extra == 'dev'
Requires-Dist: pytest (>=5.4.3) ; extra == 'dev'
Requires-Dist: pytest-cov (>=2.9.0) ; extra == 'dev'
Requires-Dist: twine (>=3.3.0) ; extra == 'dev'
Provides-Extra: test
Requires-Dist: pytest (>=5.4.3) ; extra == 'test'
Requires-Dist: pytest-cov (>=2.9.0) ; extra == 'test'
